Workbook
Name Anos: Planilha1!$D$18:$D$18
Name Dividendos: Planilha1!$D$21:$D$21
Name ivst_mensal: Planilha1!$D$17:$D$17
Name Rendimento_de_carteira: Planilha1!$D$13:$D$13
Name Salario: Planilha1!$D$12:$D$12
Name Sugest_invest: Planilha1!$D$14:$D$14
Name Total_acumulado: Planilha1!$D$20:$D$20
Name tx_rendimento_mensal: Planilha1!$D$19:$D$19

Sheet Planilha1
B11: Configurações
B12: Salário | D12: 2000
B13: Rendimento de carteira | D13: 0.01
B14: Sugestão de investimento (20% do salário) | D14: =D12*20% -> 400
B16: Investimento mensal
B17: Quanto investir por mês? | D17: 320
B18: Por quantos anos investir? | D18: 10
B19: Qual a taxa de rendimento mensal? | D19: 0.01079
B20: Qual o patrimônio acumulado terei? | D20: =FV(D19,D18*12,D17)*-1 -> 77850.948
B21: Quanto de dividendos mensais? | D21: =D20*$D$13 -> 778.50948
B23: Quanto em: | C23: Patrimônio acumulado: | D23: Dividendos mensais:
B24: 1 ano | C24: =FV($D$19,1*12,$D$17)*-1 -> 4076.2835 | D24: =C24*$D$13 -> 40.762835
B25: 3 anos | C25: =FV($D$19,3*12,$D$17)*-1 -> 13986.68 | D25: =C25*$D$13 -> 139.8668
B26: 5 anos | C26: =FV($D$19,5*12,$D$17)*-1 -> 26808.612 | D26: =C26*$D$13 -> 268.08612
B27: 10 anos | C27: =FV($D$19,10*12,$D$17)*-1 -> 77850.948 | D27: =C27*$D$13 -> 778.50948
B28: 20 anos | C28: =FV($D$19,20*12,$D$17)*-1 -> 360063.49 | D28: =C28*$D$13 -> 3600.6349
B30: Selecione o perfil: | C30: Valor a ser investido por mês
B31: Conservador | C31: =D17 -> 320
B33: Tipo de FII | C33: Percentual sugerido | D33: Valores
B34: Papel | C34: =VLOOKUP($B$31&"-"&B34,Planilha2!$A:$D,4,FALSE) -> 0.3 | D34: =$C$31*C34 -> 96
B35: Tijolo | C35: =VLOOKUP($B$31&"-"&B35,Planilha2!$A:$D,4,FALSE) -> 0.5 | D35: =$C$31*C35 -> 160
B36: Hibridos | C36: =VLOOKUP($B$31&"-"&B36,Planilha2!$A:$D,4,FALSE) -> 0.1 | D36: =$C$31*C36 -> 32
B37: FOFs | C37: =VLOOKUP($B$31&"-"&B37,Planilha2!$A:$D,4,FALSE) -> 0.1 | D37: =$C$31*C37 -> 32
B38: Desenvolvimento | C38: =VLOOKUP($B$31&"-"&B38,Planilha2!$A:$D,4,FALSE) -> 0 | D38: =$C$31*C38 -> 0
B39: Hotelarias | C39: =VLOOKUP($B$31&"-"&B39,Planilha2!$A:$D,4,FALSE) -> 0 | D39: =$C$31*C39 -> 0

Sheet Planilha2
A1: Chave | B1: Tipo de FII | C1: Perfil | D1: %
A2: Conservador-Papel | B2: Papel | C2: Conservador | D2: 0.3
A3: Conservador-Tijolo | B3: Tijolo | C3: Conservador | D3: 0.5
A4: Conservador-Hibridos | B4: Hibridos | C4: Conservador | D4: 0.1
A5: Conservador-FOFs | B5: FOFs | C5: Conservador | D5: 0.1
A6: Conservador-Desenvolvimento | B6: Desenvolvimento | C6: Conservador | D6: 0
A7: Conservador-Hotelarias | B7: Hotelarias | C7: Conservador | D7: 0
A8: Moderado-Papel | B8: Papel | C8: Moderado | D8: 0.32
A9: Moderado-Tijolo | B9: Tijolo | C9: Moderado | D9: 0.35
A10: Moderado-Hibridos | B10: Hibridos | C10: Moderado | D10: 0.08
A11: Moderado-FOFs | B11: FOFs | C11: Moderado | D11: 0.05
A12: Moderado-Desenvolvimento | B12: Desenvolvimento | C12: Moderado | D12: 0.1
A13: Moderado-Hotelarias | B13: Hotelarias | C13: Moderado | D13: 0.1
... A19: Agressivo-Hotelarias | B19: Hotelarias | C19: Agressivo | D19: 0.1
